aik_infra/__init__.py
aik_infra/database.py
aik_infra/events.py
aik_infra/kafka_client.py
aik_infra/logging/__init__.py
aik_infra/logging/config.py
aik_infra/password_hasher.py
aik_infra/project_tree.py
aik_infra/redis_client.py
aik_infra/redis_instance.py
aik_infra-0.1.5.dist-info/METADATA
aik_infra-0.1.5.dist-info/WHEEL
aik_infra-0.1.5.dist-info/entry_points.txt
aik_infra-0.1.5.dist-info/RECORD
